venncsv/__init__.py
venncsv/__main__.py
venncsv-0.9.3.dist-info/entry_points.txt
venncsv-0.9.3.dist-info/WHEEL
venncsv-0.9.3.dist-info/METADATA
venncsv-0.9.3.dist-info/RECORD
