Metadata-Version: 2.1
Name: venncsv
Version: 0.9.3
Summary: '$ venncsv x.csv y.csv' writes x_and_y.csv x_or_y.csv x_xor_y.csv x_minus_y.csv and y_minus_y.csv
Home-page: https://pypi.org/project/venncsv
Author: Carlo Alessandro Verre
Author-email: carlo.alessandro.verre@gmail.com
Requires-Python: >=3.6
Classifier: Programming Language :: Python :: 3
Classifier: Programming Language :: Python :: 3.6
Classifier: Development Status :: 4 - Beta
Classifier: Environment :: Console
Classifier: Intended Audience :: End Users/Desktop
Classifier: License :: OSI Approved :: GNU General Public License v3 or later (GPLv3+)
Classifier: Operating System :: POSIX :: Linux
Requires-Dist: libfunx
